functional_web_tests/__init__.py
functional_web_tests/conftest.py
functional_web_tests/steps.json
functional_web_tests/tests/__init__.py
functional_web_tests/tests/config/__init__.py
functional_web_tests/tests/config/locators.py
functional_web_tests/tests/config/private.py
functional_web_tests/tests/config/supported_platforms.py
functional_web_tests/tests/config/url.py
functional_web_tests/tests/execute_tests/__init__.py
functional_web_tests/tests/execute_tests/login/__init__.py
functional_web_tests/tests/execute_tests/login/test_health_check.py
functional_web_tests/tests/execute_tests/login/test_login.py
functional_web_tests/tests/execute_tests/login/test_login_bad_email.py
functional_web_tests/tests/execute_tests/login/test_login_bad_password.py
functional_web_tests/tests/execute_tests/login/test_login_bad_user.py
functional_web_tests/tests/execute_tests/login/test_login_with_email.py
functional_web_tests/tests/execute_tests/login/test_login_with_email_and_wrong_password.py
functional_web_tests/tests/execute_tests/login/test_login_with_facebook.py
functional_web_tests/tests/execute_tests/login/test_login_with_github.py
functional_web_tests/tests/execute_tests/login/test_login_with_google.py
functional_web_tests/tests/execute_tests/login/test_login_with_invalid_email_and_password_characters.py
functional_web_tests/tests/execute_tests/login/test_login_with_invalid_email_characters.py
functional_web_tests/tests/execute_tests/login/test_login_with_invalid_length.py
functional_web_tests/tests/execute_tests/login/test_login_with_invalid_password_characters.py
functional_web_tests/tests/execute_tests/login/test_login_with_linkedin.py
functional_web_tests/tests/execute_tests/login/test_login_with_missing_fields.py
functional_web_tests/tests/execute_tests/login/test_login_with_signout.py
functional_web_tests/tests/execute_tests/login/test_login_with_twitter.py
functional_web_tests/tests/execute_tests/login/test_login_with_username_invalid_length.py
functional_web_tests-0.0.5.dist-info/METADATA
functional_web_tests-0.0.5.dist-info/WHEEL
functional_web_tests-0.0.5.dist-info/top_level.txt
functional_web_tests-0.0.5.dist-info/RECORD
