Metadata-Version: 2.1
Name: functional-web-tests
Version: 0.0.5
Summary: this project is intended to provide an open source repository of automated functional web tests to help testers with repeating and similar scenarios to test and maintain a generic collection of tests intended to be copied into other testing projects or to be used for examples to these projects.
Home-page: https://qaviton.com/
Author: Yehonadav Bar Elan
Author-email: yehonadav@Qaviton.com
License: Apache 2.0
Keywords: functional_web_tests
Platform: UNKNOWN
Classifier: Development Status :: 3 - Alpha
Classifier: Programming Language :: Python
Classifier: Environment :: Console
Classifier: Environment :: MacOS X
Classifier: Environment :: Win32 (MS Windows)
Classifier: Intended Audience :: Developers
Classifier: Intended Audience :: Other Audience
Classifier: License :: OSI Approved :: Apache Software License
Classifier: Operating System :: OS Independent
Classifier: Topic :: Software Development :: Quality Assurance
Classifier: Topic :: Software Development :: Testing
Classifier: Topic :: Software Development :: Libraries :: Application Frameworks
Requires-Dist: qaviton (>=0.1.1)
